PPTXConvertor/__init__.py
PPTXConvertor-0.0.5.dist-info/LICENSE
PPTXConvertor-0.0.5.dist-info/METADATA
PPTXConvertor-0.0.5.dist-info/WHEEL
PPTXConvertor-0.0.5.dist-info/top_level.txt
PPTXConvertor-0.0.5.dist-info/RECORD
