Metadata-Version: 2.1
Name: PPTXConvertor
Version: 0.0.5
Summary: Simple pptx file convertor. Powerpoint application is required.
Home-page: https://github.com/AndersonBY/PPTXConvertor
Author: MakerBi
Author-email: andersonby@163.com
License: UNKNOWN
Platform: UNKNOWN
Classifier: Programming Language :: Python :: 3
Classifier: License :: OSI Approved :: MIT License
Classifier: Operating System :: OS Independent
Requires-Python: >=3.6
License-File: LICENSE
